source/__init__.py
source/github.py
source/plugin.py
pytest_gh_log_group-0.2.0.dist-info/LICENSE
pytest_gh_log_group-0.2.0.dist-info/METADATA
pytest_gh_log_group-0.2.0.dist-info/WHEEL
pytest_gh_log_group-0.2.0.dist-info/entry_points.txt
pytest_gh_log_group-0.2.0.dist-info/top_level.txt
pytest_gh_log_group-0.2.0.dist-info/RECORD
