Metadata-Version: 2.1
Name: pytest-gh-log-group
Version: 0.2.0
Summary: pytest plugin for gh actions
Home-page: https://github.com/embedded-community/pytest_gh_log_group
Author: Jussi Vatjus-Anttila
Author-email: jussiva@gmail.com
License: UNKNOWN
Project-URL: Source, https://github.com/embedded-community/pytest_gh_log_group
Keywords: py.test pytest github actions log grouping
Platform: UNKNOWN
Classifier: Framework :: Pytest
Classifier: Development Status :: 3 - Alpha
Classifier: Intended Audience :: Developers
Classifier: Operating System :: POSIX
Classifier: Operating System :: Microsoft :: Windows
Classifier: Operating System :: MacOS :: MacOS X
Classifier: Topic :: Software Development :: Quality Assurance
Classifier: Topic :: Software Development :: Testing
Classifier: Topic :: Utilities
Classifier: Programming Language :: Python :: 3.10
Classifier: Programming Language :: Python :: 3.9
Classifier: Programming Language :: Python :: 3.8
Classifier: Programming Language :: Python :: 3.7
Requires-Python: >=3.7, <4
License-File: LICENSE
Requires-Dist: pytest
Provides-Extra: dev
Requires-Dist: pytest-cov ; extra == 'dev'
Requires-Dist: pylint ; extra == 'dev'
